{
  "project_info": {
    "project_number": "987526046033",
    "project_id": "lab8-e903c",
    "storage_bucket": "lab8-e903c.appspot.com"
  },
  "client": [
    {
      "client_info": {
        "mobilesdk_app_id": "1:987526046033:android:bfc8cc2bbdc0497ebd3370",
        "android_client_info": {
          "package_name": "com.example.lab8"
        }
      },
      "oauth_client": [],
      "api_key": [
        {
          "current_key": "AIzaSyAIx7kowxBbEhb6bcsSG3I_FnkO1ka5FO4"
        }
      ],
      "services": {
        "appinvite_service": {
          "other_platform_oauth_client": []
        }
      }
    }
  ],
  "configuration_version": "1"
}